{
  "2024-3-12": [
    [
      "2024-03-12 01:02AM",
      "Faculty sue Penn over 'McCarthyism,' aiming to stop transfer of University documents to Congress"
    ],
    [
      "2024-03-12 01:20AM",
      ""
    ],
    [
      "2024-03-12 01:30AM",
      "Black History Month at Penn, presented by The Daily Pennsylvanian"
    ]
  ],
  "2024-3-13": [
    [
      "2024-03-13 04:12PM",
      "DP Daybreak | Discrimination allegations in Penn Med program"
    ]
  ],
  "2024-3-14": [
    [
      "2024-03-14 04:13PM",
      "Michelle Lyu | We want to be free"
    ]
  ],
  "2024-3-15": [
    [
      "2024-03-15 04:15PM",
      "Beatriz B\u00e1ez | No closed captioning available"
    ]
  ],
  "2024-3-16": [
    [
      "2024-03-16 04:12PM",
      "Lala Mustafa | Breaking our social routine"
    ]
  ],
  "2024-3-17": [
    [
      "2024-03-17 04:13PM",
      "Zara Tena | You should take an ethics class at Penn"
    ]
  ],
  "2024-3-18": [
    [
      "2024-03-18 04:13PM",
      "Penn men\u2019s basketball freshman guard Tyler Perkins enters transfer portal"
    ]
  ],
  "2024-3-19": [
    [
      "2024-03-19 04:13PM",
      "DP Daybreak | Wharton defends Fight Night amid student backlash"
    ]
  ],
  "2024-3-20": [
    [
      "2024-03-20 04:13PM",
      "DP Daybreak | UC Townhomes demolition begins"
    ]
  ],
  "2024-3-21": [
    [
      "2024-03-21 04:13PM",
      "Vaulting against the odds: How Scott Toney overcame loss and injuries to become an Ivy champion"
    ]
  ],
  "2024-3-22": [
    [
      "2024-03-22 04:13PM",
      "Sose Hovannisian | A love letter to Philadelphia"
    ]
  ],
  "2024-3-23": [
    [
      "2024-03-23 04:13PM",
      "Sose Hovannisian | A love letter to Philadelphia"
    ]
  ],
  "2024-3-24": [
    [
      "2024-03-24 04:12PM",
      "No. 12 Penn men's lacrosse handles its business with 11-8 win against Dartmouth"
    ]
  ],
  "2024-3-25": [
    [
      "2024-03-25 04:13PM",
      "Penn men's and women's track and field gets outdoor season started with the Penn Challenge"
    ]
  ],
  "2024-3-26": [
    [
      "2024-03-26 04:13PM",
      "Jack Lakis | Let\u2019s talk about writing seminars"
    ]
  ],
  "2024-4-2": [
    [
      "2024-04-02 03:20PM",
      "Penn swimming junior breaststroker Matt Fallon takes second at NCAA Championships"
    ]
  ],
  "2024-4-3": [
    [
      "2024-04-03 04:15PM",
      "DP Daybreak | Students voice frustration with off-campus landlords"
    ]
  ],
  "2024-4-4": [
    [
      "2024-04-04 04:13PM",
      "DP Daybreak | Inside Penn donors' political stances"
    ]
  ],
  "2024-4-5": [
    [
      "2024-04-05 04:13PM",
      "4.8 magnitude earthquake in New Jersey shakes Penn campus, prompting alert"
    ]
  ],
  "2024-4-6": [
    [
      "2024-04-06 04:14PM",
      "Mariana Martinez | Status update: In a toxic relationship with academia"
    ]
  ],
  "2024-4-7": [
    [
      "2024-04-07 04:12PM",
      "Unpacking the best nicknames in Penn sports "
    ]
  ],
  "2024-4-8": [
    [
      "2024-04-08 04:15PM",
      "Eliza Carroll | The cultural stratification of Penn"
    ]
  ],
  "2024-4-9": [
    [
      "2024-04-09 04:13PM",
      "DP Daybreak | Alumni call for stronger free speech protections"
    ]
  ],
  "2024-4-10": [
    [
      "2024-04-10 04:13PM",
      "Clark Slajchert of Penn men's basketball announces graduate transfer to USC"
    ]
  ],
  "2024-4-11": [
    [
      "2024-04-11 04:13PM",
      "Meet DP Opinion's spring 2024 columnists"
    ]
  ],
  "2024-4-12": [
    [
      "2024-04-12 04:13PM",
      "Meet DP Opinion's spring 2024 columnists"
    ]
  ]
}